[{"date":"2022-12-07","count":1},{"date":"2022-12-01","count":8},{"date":"2022-11-29","count":4},{"date":"2022-12-19","count":8},{"date":"2022-12-12","count":1},{"date":"2022-12-11","count":0},{"date":"2022-11-30","count":2},{"date":"2022-12-09","count":2},{"date":"2022-12-06","count":5},{"date":"2022-12-05","count":2},{"date":"2022-12-15","count":18},{"date":"2022-12-14","count":7},{"date":"2022-12-08","count":6},{"date":"2022-12-20","count":2},{"date":"2022-12-17","count":3},{"date":"2022-12-16","count":4},{"date":"2022-12-18","count":6},{"date":"2022-12-13","count":3}]
